walscript/__init__.py
walscript/wal.py
walscript-0.2.1.dist-info/DESCRIPTION.rst
walscript-0.2.1.dist-info/METADATA
walscript-0.2.1.dist-info/RECORD
walscript-0.2.1.dist-info/WHEEL
walscript-0.2.1.dist-info/metadata.json
walscript-0.2.1.dist-info/top_level.txt
