Metadata-Version: 2.0
Name: walscript
Version: 0.2.1
Summary: web automation layer
Home-page: https://fasterdevops.github.io/
Author: Kolby
Author-email: kolby@fasterdevops.com
License: MIT
Download-URL: https://github.com/classmember/wal/archive/master.zip
Keywords: web automation layer
Platform: UNKNOWN
Classifier: Development Status :: 3 - Alpha
Classifier: Intended Audience :: Developers
Classifier: Operating System :: POSIX
Classifier: Operating System :: POSIX :: Linux
Classifier: Operating System :: Unix
Classifier: License :: OSI Approved :: MIT License
Classifier: Programming Language :: Python :: 3
Classifier: Programming Language :: Python :: 3.2
Classifier: Programming Language :: Python :: 3.3
Classifier: Programming Language :: Python :: 3.4
Classifier: Topic :: Internet
Requires-Dist: PyYAML (==3.12)
Requires-Dist: selenium (==2.53.2)
Requires-Dist: simplejson (==3.10.0)
Requires-Dist: six (==1.10.0)
Requires-Dist: urllib3 (==1.15.1)
